hci/__init__.py
hci/autocast.py
hci/from_binary.py
hci/hci_packet.py
hci/transforms.py
hci/asynchronous/__init__.py
hci/asynchronous/asynchronous_data_packet.py
hci/asynchronous/autocast.py
hci/command/__init__.py
hci/command/autocast.py
hci/command/command_packet.py
hci/command/opcode.py
hci/command/commands/__init__.py
hci/command/commands/att_exchange_mtu_req.py
hci/command/commands/gap_device_discovery_request.py
hci/command/commands/gap_device_init.py
hci/command/commands/gap_establish_link_req.py
hci/command/commands/gap_get_param.py
hci/command/commands/gap_set_param.py
hci/command/commands/gap_terminate_link_req.py
hci/command/commands/gap_update_link_param_req.py
hci/command/commands/gap_update_link_param_req_reply.py
hci/command/commands/gatt_read_char_value.py
hci/command/commands/gatt_write_char_value.py
hci/command/commands/hci_ext_one_pkt_per_evt.py
hci/command/commands/hci_ext_packet_error_rate.py
hci/command/commands/hci_ext_reset_system.py
hci/command/commands/hci_ext_set_tx_power.py
hci/command/commands/hci_read_rssi.py
hci/command/commands/hci_reset.py
hci/command/commands/le_set_data_length.py
hci/command/commands/le_set_default_phy.py
hci/command/commands/le_set_phy.py
hci/command/commands/util_build_revision.py
hci/command/commands/util_force_boot.py
hci/event/__init__.py
hci/event/autocast.py
hci/event/event_codes.py
hci/event/event_packet.py
hci/event/events/__init__.py
hci/event/events/hci_command_complete.py
hci/event/events/vendor_specific_event.py
hci/event/events/vendor_specific_events.py
hci/event/events/hci_commands_complete/__init__.py
hci/event/events/hci_commands_complete/autocast.py
hci/event/events/hci_commands_complete/hci_read_rssi.py
hci/event/events/vendor_specific/__init__.py
hci/event/events/vendor_specific/att_error_response.py
hci/event/events/vendor_specific/att_exchange_mtu_response.py
hci/event/events/vendor_specific/att_handle_value_notification.py
hci-0.0.6.dist-info/DESCRIPTION.rst
hci-0.0.6.dist-info/METADATA
hci-0.0.6.dist-info/RECORD
hci-0.0.6.dist-info/WHEEL
hci-0.0.6.dist-info/metadata.json
hci-0.0.6.dist-info/top_level.txt
