Metadata-Version: 2.0
Name: hci
Version: 0.0.6
Summary: Library for creating and parsing HCI packets.
Home-page: https://github.com/acburigo/python-hci
Author: Arthur Crippa Búrigo & Pedro Gyrão
Author-email: arthurcburigo@gmail.com
License: MIT
Keywords: HCI,protocol,ti,texas instruments,encode,decode,ble,bluetooth low energy
Platform: UNKNOWN
Classifier: Development Status :: 3 - Alpha
Classifier: Intended Audience :: Developers
Classifier: License :: OSI Approved :: MIT License
Classifier: Programming Language :: Python :: 3
Classifier: Programming Language :: Python :: 3.5
